<?xml version="1.0" encoding="UTF-8"?>
<!-- generated: 2008-09-24T16:40:05-07:00 -->
<!-- generated by: shishir [??] -->
<adag xmlns="http://pegasus.isi.edu/schema/DAX" xmlns:xsi="http://www.w3.org/2001/XMLSchema-instance" xsi:schemaLocation="http://pegasus.isi.edu/schema/DAX http://pegasus.isi.edu/schema/dax-2.1.xsd" version="2.1" count="1" index="0" name="test" jobCount="50" fileCount="0" childCount="46">
<!-- part 1: list of all referenced files (may be empty) -->
<!-- part 2: definition of all jobs (at least one) -->
  <job id="ID00000" namespace="CyberShake" name="ZipPSA" version="1.0" runtime="0.24">
    <uses file="Cybershake_PSA.zip" link="output" register="true" transfer="true" optional="false" type="data" size="661"/>
  </job>
  <job id="ID00001" namespace="CyberShake" name="ZipSeis" version="1.0" runtime="0.17">
    <uses file="Cybershake_Seismograms.zip" link="output" register="true" transfer="true" optional="false" type="data" size="37714"/>
  </job>
  <job id="ID00002" namespace="CyberShake" name="ExtractSGT" version="1.0" runtime="73.14">
    <uses file="FFI_0_1_fx.sgt" link="input" register="true" transfer="true" optional="false" type="data" size="19689396327"/>
    <uses file="FFI_0_1_fy.sgt" link="input" register="true" transfer="true" optional="false" type="data" size="19689396327"/>
    <uses file="FFI_0_1_subfx.sgt" link="output" register="true" transfer="true" optional="false" type="data" size="273968744"/>
    <uses file="FFI_0_1_subfy.sgt" link="output" register="true" transfer="true" optional="false" type="data" size="273968744"/>
    <uses file="FFI_0_1_txt.variation-s06408-h00000" link="input" register="true" transfer="true" optional="false" type="data" size="3045252"/>
  </job>
  <job id="ID00003" namespace="CyberShake" name="SeismogramSynthesis" version="1.0" runtime="59.57">
    <uses file="FFI_0_1_txt.variation-s09810-h00000" link="input" register="true" transfer="true" optional="false" type="data" size="2181693"/>
    <uses file="FFI_0_1_subfx.sgt" link="input" register="true" transfer="true" optional="false" type="data" size="273968744"/>
    <uses file="FFI_0_1_subfy.sgt" link="input" register="true" transfer="true" optional="false" type="data" size="273968744"/>
    <uses file="Seismogram_FFI_0_1_ID00003.grm" link="output" register="true" transfer="true" optional="false" type="data" size="24000"/>
  </job>
  <job id="ID00004" namespace="CyberShake" name="PeakValCalcOkaya" version="1.0" runtime="1.40">
    <uses file="Seismogram_FFI_0_1_ID00003.grm" link="input" register="true" transfer="true" optional="false" type="data" size="24000"/>
    <uses file="PeakVals_FFI_0_1_ID00003.bsa" link="output" register="true" transfer="true" optional="false" type="data" size="216"/>
  </job>
  <job id="ID00005" namespace="CyberShake" name="SeismogramSynthesis" version="1.0" runtime="39.90">
    <uses file="FFI_0_1_txt.variation-s02432-h00000" link="input" register="true" transfer="true" optional="false" type="data" size="5561198"/>
    <uses file="FFI_0_1_subfx.sgt" link="input" register="true" transfer="true" optional="false" type="data" size="140305309"/>
    <uses file="FFI_0_1_subfy.sgt" link="input" register="true" transfer="true" optional="false" type="data" size="140305309"/>
    <uses file="Seismogram_FFI_0_1_ID00005.grm" link="output" register="true" transfer="true" optional="false" type="data" size="24000"/>
  </job>
  <job id="ID00006" namespace="CyberShake" name="PeakValCalcOkaya" version="1.0" runtime="1.01">
    <uses file="Seismogram_FFI_0_1_ID00005.grm" link="input" register="true" transfer="true" optional="false" type="data" size="24000"/>
    <uses file="PeakVals_FFI_0_1_ID00005.bsa" link="output" register="true" transfer="true" optional="false" type="data" size="216"/>
  </job>
  <job id="ID00007" namespace="CyberShake" name="SeismogramSynthesis" version="1.0" runtime="64.21">
    <uses file="FFI_0_1_txt.variation-s02175-h00000" link="input" register="true" transfer="true" optional="false" type="data" size="4897170"/>
    <uses file="FFI_0_1_subfx.sgt" link="input" register="true" transfer="true" optional="false" type="data" size="121378233"/>
    <uses file="FFI_0_1_subfy.sgt" link="input" register="true" transfer="true" optional="false" type="data" size="121378233"/>
    <uses file="Seismogram_FFI_0_1_ID00007.grm" link="output" register="true" transfer="true" optional="false" type="data" size="24000"/>
  </job>
  <job id="ID00008" namespace="CyberShake" name="PeakValCalcOkaya" version="1.0" runtime="1.32">
    <uses file="Seismogram_FFI_0_1_ID00007.grm" link="input" register="true" transfer="true" optional="false" type="data" size="24000"/>
    <uses file="PeakVals_FFI_0_1_ID00007.bsa" link="output" register="true" transfer="true" optional="false" type="data" size="216"/>
  </job>
  <job id="ID00009" namespace="CyberShake" name="SeismogramSynthesis" version="1.0" runtime="61.21">
    <uses file="FFI_0_1_txt.variation-s06408-h00000" link="input" register="true" transfer="true" optional="false" type="data" size="3045252"/>
    <uses file="FFI_0_1_subfx.sgt" link="input" register="true" transfer="true" optional="false" type="data" size="174035771"/>
    <uses file="FFI_0_1_subfy.sgt" link="input" register="true" transfer="true" optional="false" type="data" size="174035771"/>
    <uses file="Seismogram_FFI_0_1_ID00009.grm" link="output" register="true" transfer="true" optional="false" type="data" size="24000"/>
  </job>
  <job id="ID00010" namespace="CyberShake" name="PeakValCalcOkaya" version="1.0" runtime="0.99">
    <uses file="Seismogram_FFI_0_1_ID00009.grm" link="input" register="true" transfer="true" optional="false" type="data" size="24000"/>
    <uses file="PeakVals_FFI_0_1_ID00009.bsa" link="output" register="true" transfer="true" optional="false" type="data" size="216"/>
  </job>
  <job id="ID00011" namespace="CyberShake" name="ExtractSGT" version="1.0" runtime="185.98">
    <uses file="FFI_0_2_fx.sgt" link="input" register="true" transfer="true" optional="false" type="data" size="20069246619"/>
    <uses file="FFI_0_2_fy.sgt" link="input" register="true" transfer="true" optional="false" type="data" size="20069246619"/>
    <uses file="FFI_0_2_subfx.sgt" link="output" register="true" transfer="true" optional="false" type="data" size="258348492"/>
    <uses file="FFI_0_2_subfy.sgt" link="output" register="true" transfer="true" optional="false" type="data" size="258348492"/>
    <uses file="FFI_0_2_txt.variation-s07697-h00000" link="input" register="true" transfer="true" optional="false" type="data" size="4431448"/>
  </job>
  <job id="ID00012" namespace="CyberShake" name="SeismogramSynthesis" version="1.0" runtime="49.37">
    <uses file="FFI_0_2_txt.variation-s02524-h00000" link="input" register="true" transfer="true" optional="false" type="data" size="4908971"/>
    <uses file="FFI_0_2_subfx.sgt" link="input" register="true" transfer="true" optional="false" type="data" size="258348492"/>
    <uses file="FFI_0_2_subfy.sgt" link="input" register="true" transfer="true" optional="false" type="data" size="258348492"/>
    <uses file="Seismogram_FFI_0_2_ID00012.grm" link="output" register="true" transfer="true" optional="false" type="data" size="24000"/>
  </job>
  <job id="ID00013" namespace="CyberShake" name="PeakValCalcOkaya" version="1.0" runtime="0.88">
    <uses file="Seismogram_FFI_0_2_ID00012.grm" link="input" register="true" transfer="true" optional="false" type="data" size="24000"/>
    <uses file="PeakVals_FFI_0_2_ID00012.bsa" link="output" register="true" transfer="true" optional="false" type="data" size="216"/>
  </job>
  <job id="ID00014" namespace="CyberShake" name="SeismogramSynthesis" version="1.0" runtime="41.40">
    <uses file="FFI_0_2_txt.variation-s01535-h00000" link="input" register="true" transfer="true" optional="false" type="data" size="3658516"/>
    <uses file="FFI_0_2_subfx.sgt" link="input" register="true" transfer="true" optional="false" type="data" size="182970513"/>
    <uses file="FFI_0_2_subfy.sgt" link="input" register="true" transfer="true" optional="false" type="data" size="182970513"/>
    <uses file="Seismogram_FFI_0_2_ID00014.grm" link="output" register="true" transfer="true" optional="false" type="data" size="24000"/>
  </job>
  <job id="ID00015" namespace="CyberShake" name="PeakValCalcOkaya" version="1.0" runtime="1.30">
    <uses file="Seismogram_FFI_0_2_ID00014.grm" link="input" register="true" transfer="true" optional="false" type="data" size="24000"/>
    <uses file="PeakVals_FFI_0_2_ID00014.bsa" link="output" register="true" transfer="true" optional="false" type="data" size="216"/>
  </job>
  <job id="ID00016" namespace="CyberShake" name="SeismogramSynthesis" version="1.0" runtime="55.11">
    <uses file="FFI_0_2_txt.variation-s01360-h00000" link="input" register="true" transfer="true" optional="false" type="data" size="2896948"/>
    <uses file="FFI_0_2_subfx.sgt" link="input" register="true" transfer="true" optional="false" type="data" size="127330618"/>
    <uses file="FFI_0_2_subfy.sgt" link="input" register="true" transfer="true" optional="false" type="data" size="127330618"/>
    <uses file="Seismogram_FFI_0_2_ID00016.grm" link="output" register="true" transfer="true" optional="false" type="data" size="24000"/>
  </job>
  <job id="ID00017" namespace="CyberShake" name="PeakValCalcOkaya" version="1.0" runtime="1.57">
    <uses file="Seismogram_FFI_0_2_ID00016.grm" link="input" register="true" transfer="true" optional="false" type="data" size="24000"/>
    <uses file="PeakVals_FFI_0_2_ID00016.bsa" link="output" register="true" transfer="true" optional="false" type="data" size="216"/>
  </job>
  <job id="ID00018" namespace="CyberShake" name="SeismogramSynthesis" version="1.0" runtime="50.96">
    <uses file="FFI_0_2_txt.variation-s02266-h00000" link="input" register="true" transfer="true" optional="false" type="data" size="3154145"/>
    <uses file="FFI_0_2_subfx.sgt" link="input" register="true" transfer="true" optional="false" type="data" size="192832526"/>
    <uses file="FFI_0_2_subfy.sgt" link="input" register="true" transfer="true" optional="false" type="data" size="192832526"/>
    <uses file="Seismogram_FFI_0_2_ID00018.grm" link="output" register="true" transfer="true" optional="false" type="data" size="24000"/>
  </job>
  <job id="ID00019" namespace="CyberShake" name="PeakValCalcOkaya" version="1.0" runtime="1.44">
    <uses file="Seismogram_FFI_0_2_ID00018.grm" link="input" register="true" transfer="true" optional="false" type="data" size="24000"/>
    <uses file="PeakVals_FFI_0_2_ID00018.bsa" link="output" register="true" transfer="true" optional="false" type="data" size="216"/>
  </job>
  <job id="ID00020" namespace="CyberShake" name="SeismogramSynthesis" version="1.0" runtime="36.65">
    <uses file="FFI_0_2_txt.variation-s07697-h00000" link="input" register="true" transfer="true" optional="false" type="data" size="4431448"/>
    <uses file="FFI_0_2_subfx.sgt" link="input" register="true" transfer="true" optional="false" type="data" size="262360916"/>
    <uses file="FFI_0_2_subfy.sgt" link="input" register="true" transfer="true" optional="false" type="data" size="262360916"/>
    <uses file="Seismogram_FFI_0_2_ID00020.grm" link="output" register="true" transfer="true" optional="false" type="data" size="24000"/>
  </job>
  <job id="ID00021" namespace="CyberShake" name="PeakValCalcOkaya" version="1.0" runtime="1.56">
    <uses file="Seismogram_FFI_0_2_ID00020.grm" link="input" register="true" transfer="true" optional="false" type="data" size="24000"/>
    <uses file="PeakVals_FFI_0_2_ID00020.bsa" link="output" register="true" transfer="true" optional="false" type="data" size="216"/>
  </job>
  <job id="ID00022" namespace="CyberShake" name="ExtractSGT" version="1.0" runtime="90.56">
    <uses file="FFI_0_3_fx.sgt" link="input" register="true" transfer="true" optional="false" type="data" size="20322502120"/>
    <uses file="FFI_0_3_fy.sgt" link="input" register="true" transfer="true" optional="false" type="data" size="20322502120"/>
    <uses file="FFI_0_3_subfx.sgt" link="output" register="true" transfer="true" optional="false" type="data" size="295949580"/>
    <uses file="FFI_0_3_subfy.sgt" link="output" register="true" transfer="true" optional="false" type="data" size="295949580"/>
    <uses file="FFI_0_3_txt.variation-s09274-h00000" link="input" register="true" transfer="true" optional="false" type="data" size="2128736"/>
  </job>
  <job id="ID00023" namespace="CyberShake" name="SeismogramSynthesis" version="1.0" runtime="42.76">
    <uses file="FFI_0_3_txt.variation-s07428-h00000" link="input" register="true" transfer="true" optional="false" type="data" size="4633308"/>
    <uses file="FFI_0_3_subfx.sgt" link="input" register="true" transfer="true" optional="false" type="data" size="295949580"/>
    <uses file="FFI_0_3_subfy.sgt" link="input" register="true" transfer="true" optional="false" type="data" size="295949580"/>
    <uses file="Seismogram_FFI_0_3_ID00023.grm" link="output" register="true" transfer="true" optional="false" type="data" size="24000"/>
  </job>
  <job id="ID00024" namespace="CyberShake" name="PeakValCalcOkaya" version="1.0" runtime="1.03">
    <uses file="Seismogram_FFI_0_3_ID00023.grm" link="input" register="true" transfer="true" optional="false" type="data" size="24000"/>
    <uses file="PeakVals_FFI_0_3_ID00023.bsa" link="output" register="true" transfer="true" optional="false" type="data" size="216"/>
  </job>
  <job id="ID00025" namespace="CyberShake" name="SeismogramSynthesis" version="1.0" runtime="29.64">
    <uses file="FFI_0_3_txt.variation-s02292-h00000" link="input" register="true" transfer="true" optional="false" type="data" size="3545382"/>
    <uses file="FFI_0_3_subfx.sgt" link="input" register="true" transfer="true" optional="false" type="data" size="186577906"/>
    <uses file="FFI_0_3_subfy.sgt" link="input" register="true" transfer="true" optional="false" type="data" size="186577906"/>
    <uses file="Seismogram_FFI_0_3_ID00025.grm" link="output" register="true" transfer="true" optional="false" type="data" size="24000"/>
  </job>
  <job id="ID00026" namespace="CyberShake" name="PeakValCalcOkaya" version="1.0" runtime="0.77">
    <uses file="Seismogram_FFI_0_3_ID00025.grm" link="input" register="true" transfer="true" optional="false" type="data" size="24000"/>
    <uses file="PeakVals_FFI_0_3_ID00025.bsa" link="output" register="true" transfer="true" optional="false" type="data" size="216"/>
  </job>
  <job id="ID00027" namespace="CyberShake" name="SeismogramSynthesis" version="1.0" runtime="39.30">
    <uses file="FFI_0_3_txt.variation-s02884-h00000" link="input" register="true" transfer="true" optional="false" type="data" size="2004014"/>
    <uses file="FFI_0_3_subfx.sgt" link="input" register="true" transfer="true" optional="false" type="data" size="236527811"/>
    <uses file="FFI_0_3_subfy.sgt" link="input" register="true" transfer="true" optional="false" type="data" size="236527811"/>
    <uses file="Seismogram_FFI_0_3_ID00027.grm" link="output" register="true" transfer="true" optional="false" type="data" size="24000"/>
  </job>
  <job id="ID00028" namespace="CyberShake" name="PeakValCalcOkaya" version="1.0" runtime="1.38">
    <uses file="Seismogram_FFI_0_3_ID00027.grm" link="input" register="true" transfer="true" optional="false" type="data" size="24000"/>
    <uses file="PeakVals_FFI_0_3_ID00027.bsa" link="output" register="true" transfer="true" optional="false" type="data" size="216"/>
  </job>
  <job id="ID00029" namespace="CyberShake" name="SeismogramSynthesis" version="1.0" runtime="54.24">
    <uses file="FFI_0_3_txt.variation-s04732-h00000" link="input" register="true" transfer="true" optional="false" type="data" size="3020042"/>
    <uses file="FFI_0_3_subfx.sgt" link="input" register="true" transfer="true" optional="false" type="data" size="284103494"/>
    <uses file="FFI_0_3_subfy.sgt" link="input" register="true" transfer="true" optional="false" type="data" size="284103494"/>
    <uses file="Seismogram_FFI_0_3_ID00029.grm" link="output" register="true" transfer="true" optional="false" type="data" size="24000"/>
  </job>
  <job id="ID00030" namespace="CyberShake" name="PeakValCalcOkaya" version="1.0" runtime="1.31">
    <uses file="Seismogram_FFI_0_3_ID00029.grm" link="input" register="true" transfer="true" optional="false" type="data" size="24000"/>
    <uses file="PeakVals_FFI_0_3_ID00029.bsa" link="output" register="true" transfer="true" optional="false" type="data" size="216"/>
  </job>
  <job id="ID00031" namespace="CyberShake" name="SeismogramSynthesis" version="1.0" runtime="41.72">
    <uses file="FFI_0_3_txt.variation-s00617-h00000" link="input" register="true" transfer="true" optional="false" type="data" size="5305002"/>
    <uses file="FFI_0_3_subfx.sgt" link="input" register="true" transfer="true" optional="false" type="data" size="202959561"/>
    <uses file="FFI_0_3_subfy.sgt" link="input" register="true" transfer="true" optional="false" type="data" size="202959561"/>
    <uses file="Seismogram_FFI_0_3_ID00031.grm" link="output" register="true" transfer="true" optional="false" type="data" size="24000"/>
  </job>
  <job id="ID00032" namespace="CyberShake" name="PeakValCalcOkaya" version="1.0" runtime="0.68">
    <uses file="Seismogram_FFI_0_3_ID00031.grm" link="input" register="true" transfer="true" optional="false" type="data" size="24000"/>
    <uses file="PeakVals_FFI_0_3_ID00031.bsa" link="output" register="true" transfer="true" optional="false" type="data" size="216"/>
  </job>
  <job id="ID00033" namespace="CyberShake" name="SeismogramSynthesis" version="1.0" runtime="64.06">
    <uses file="FFI_0_3_txt.variation-s09274-h00000" link="input" register="true" transfer="true" optional="false" type="data" size="2128736"/>
    <uses file="FFI_0_3_subfx.sgt" link="input" register="true" transfer="true" optional="false" type="data" size="203560050"/>
    <uses file="FFI_0_3_subfy.sgt" link="input" register="true" transfer="true" optional="false" type="data" size="203560050"/>
    <uses file="Seismogram_FFI_0_3_ID00033.grm" link="output" register="true" transfer="true" optional="false" type="data" size="24000"/>
  </job>
  <job id="ID00034" namespace="CyberShake" name="PeakValCalcOkaya" version="1.0" runtime="1.28">
    <uses file="Seismogram_FFI_0_3_ID00033.grm" link="input" register="true" transfer="true" optional="false" type="data" size="24000"/>
    <uses file="PeakVals_FFI_0_3_ID00033.bsa" link="output" register="true" transfer="true" optional="false" type="data" size="216"/>
  </job>
  <job id="ID00035" namespace="CyberShake" name="ExtractSGT" version="1.0" runtime="124.68">
    <uses file="FFI_0_4_fx.sgt" link="input" register="true" transfer="true" optional="false" type="data" size="19917761064"/>
    <uses file="FFI_0_4_fy.sgt" link="input" register="true" transfer="true" optional="false" type="data" size="19917761064"/>
    <uses file="FFI_0_4_subfx.sgt" link="output" register="true" transfer="true" optional="false" type="data" size="146305541"/>
    <uses file="FFI_0_4_subfy.sgt" link="output" register="true" transfer="true" optional="false" type="data" size="146305541"/>
    <uses file="FFI_0_4_txt.variation-s09689-h00000" link="input" register="true" transfer="true" optional="false" type="data" size="4494716"/>
  </job>
  <job id="ID00036" namespace="CyberShake" name="SeismogramSynthesis" version="1.0" runtime="23.13">
    <uses file="FFI_0_4_txt.variation-s00934-h00000" link="input" register="true" transfer="true" optional="false" type="data" size="3314903"/>
    <uses file="FFI_0_4_subfx.sgt" link="input" register="true" transfer="true" optional="false" type="data" size="146305541"/>
    <uses file="FFI_0_4_subfy.sgt" link="input" register="true" transfer="true" optional="false" type="data" size="146305541"/>
    <uses file="Seismogram_FFI_0_4_ID00036.grm" link="output" register="true" transfer="true" optional="false" type="data" size="24000"/>
  </job>
  <job id="ID00037" namespace="CyberShake" name="PeakValCalcOkaya" version="1.0" runtime="0.77">
    <uses file="Seismogram_FFI_0_4_ID00036.grm" link="input" register="true" transfer="true" optional="false" type="data" size="24000"/>
    <uses file="PeakVals_FFI_0_4_ID00036.bsa" link="output" register="true" transfer="true" optional="false" type="data" size="216"/>
  </job>
  <job id="ID00038" namespace="CyberShake" name="SeismogramSynthesis" version="1.0" runtime="43.73">
    <uses file="FFI_0_4_txt.variation-s04676-h00000" link="input" register="true" transfer="true" optional="false" type="data" size="3052478"/>
    <uses file="FFI_0_4_subfx.sgt" link="input" register="true" transfer="true" optional="false" type="data" size="192635552"/>
    <uses file="FFI_0_4_subfy.sgt" link="input" register="true" transfer="true" optional="false" type="data" size="192635552"/>
    <uses file="Seismogram_FFI_0_4_ID00038.grm" link="output" register="true" transfer="true" optional="false" type="data" size="24000"/>
  </job>
  <job id="ID00039" namespace="CyberShake" name="PeakValCalcOkaya" version="1.0" runtime="1.37">
    <uses file="Seismogram_FFI_0_4_ID00038.grm" link="input" register="true" transfer="true" optional="false" type="data" size="24000"/>
    <uses file="PeakVals_FFI_0_4_ID00038.bsa" link="output" register="true" transfer="true" optional="false" type="data" size="216"/>
  </job>
  <job id="ID00040" namespace="CyberShake" name="SeismogramSynthesis" version="1.0" runtime="37.83">
    <uses file="FFI_0_4_txt.variation-s06658-h00000" link="input" register="true" transfer="true" optional="false" type="data" size="2562307"/>
    <uses file="FFI_0_4_subfx.sgt" link="input" register="true" transfer="true" optional="false" type="data" size="184116841"/>
    <uses file="FFI_0_4_subfy.sgt" link="input" register="true" transfer="true" optional="false" type="data" size="184116841"/>
    <uses file="Seismogram_FFI_0_4_ID00040.grm" link="output" register="true" transfer="true" optional="false" type="data" size="24000"/>
  </job>
  <job id="ID00041" namespace="CyberShake" name="PeakValCalcOkaya" version="1.0" runtime="1.54">
    <uses file="Seismogram_FFI_0_4_ID00040.grm" link="input" register="true" transfer="true" optional="false" type="data" size="24000"/>
    <uses file="PeakVals_FFI_0_4_ID00040.bsa" link="output" register="true" transfer="true" optional="false" type="data" size="216"/>
  </job>
  <job id="ID00042" namespace="CyberShake" name="SeismogramSynthesis" version="1.0" runtime="57.97">
    <uses file="FFI_0_4_txt.variation-s03972-h00000" link="input" register="true" transfer="true" optional="false" type="data" size="4214216"/>
    <uses file="FFI_0_4_subfx.sgt" link="input" register="true" transfer="true" optional="false" type="data" size="243600054"/>
    <uses file="FFI_0_4_subfy.sgt" link="input" register="true" transfer="true" optional="false" type="data" size="243600054"/>
    <uses file="Seismogram_FFI_0_4_ID00042.grm" link="output" register="true" transfer="true" optional="false" type="data" size="24000"/>
  </job>
  <job id="ID00043" namespace="CyberShake" name="PeakValCalcOkaya" version="1.0" runtime="1.36">
    <uses file="Seismogram_FFI_0_4_ID00042.grm" link="input" register="true" transfer="true" optional="false" type="data" size="24000"/>
    <uses file="PeakVals_FFI_0_4_ID00042.bsa" link="output" register="true" transfer="true" optional="false" type="data" size="216"/>
  </job>
  <job id="ID00044" namespace="CyberShake" name="SeismogramSynthesis" version="1.0" runtime="44.40">
    <uses file="FFI_0_4_txt.variation-s03188-h00000" link="input" register="true" transfer="true" optional="false" type="data" size="3579809"/>
    <uses file="FFI_0_4_subfx.sgt" link="input" register="true" transfer="true" optional="false" type="data" size="152309667"/>
    <uses file="FFI_0_4_subfy.sgt" link="input" register="true" transfer="true" optional="false" type="data" size="152309667"/>
    <uses file="Seismogram_FFI_0_4_ID00044.grm" link="output" register="true" transfer="true" optional="false" type="data" size="24000"/>
  </job>
  <job id="ID00045" namespace="CyberShake" name="PeakValCalcOkaya" version="1.0" runtime="1.25">
    <uses file="Seismogram_FFI_0_4_ID00044.grm" link="input" register="true" transfer="true" optional="false" type="data" size="24000"/>
    <uses file="PeakVals_FFI_0_4_ID00044.bsa" link="output" register="true" transfer="true" optional="false" type="data" size="216"/>
  </job>
  <job id="ID00046" namespace="CyberShake" name="SeismogramSynthesis" version="1.0" runtime="39.70">
    <uses file="FFI_0_4_txt.variation-s07655-h00000" link="input" register="true" transfer="true" optional="false" type="data" size="4270044"/>
    <uses file="FFI_0_4_subfx.sgt" link="input" register="true" transfer="true" optional="false" type="data" size="150360544"/>
    <uses file="FFI_0_4_subfy.sgt" link="input" register="true" transfer="true" optional="false" type="data" size="150360544"/>
    <uses file="Seismogram_FFI_0_4_ID00046.grm" link="output" register="true" transfer="true" optional="false" type="data" size="24000"/>
  </job>
  <job id="ID00047" namespace="CyberShake" name="PeakValCalcOkaya" version="1.0" runtime="1.29">
    <uses file="Seismogram_FFI_0_4_ID00046.grm" link="input" register="true" transfer="true" optional="false" type="data" size="24000"/>
    <uses file="PeakVals_FFI_0_4_ID00046.bsa" link="output" register="true" transfer="true" optional="false" type="data" size="216"/>
  </job>
  <job id="ID00048" namespace="CyberShake" name="SeismogramSynthesis" version="1.0" runtime="46.22">
    <uses file="FFI_0_4_txt.variation-s09689-h00000" link="input" register="true" transfer="true" optional="false" type="data" size="4494716"/>
    <uses file="FFI_0_4_subfx.sgt" link="input" register="true" transfer="true" optional="false" type="data" size="199026023"/>
    <uses file="FFI_0_4_subfy.sgt" link="input" register="true" transfer="true" optional="false" type="data" size="199026023"/>
    <uses file="Seismogram_FFI_0_4_ID00048.grm" link="output" register="true" transfer="true" optional="false" type="data" size="24000"/>
  </job>
  <job id="ID00049" namespace="CyberShake" name="PeakValCalcOkaya" version="1.0" runtime="1.21">
    <uses file="Seismogram_FFI_0_4_ID00048.grm" link="input" register="true" transfer="true" optional="false" type="data" size="24000"/>
    <uses file="PeakVals_FFI_0_4_ID00048.bsa" link="output" register="true" transfer="true" optional="false" type="data" size="216"/>
  </job>
<!-- part 3: list of control-flow dependencies (may be empty) -->
  <child ref="ID00000">
    <parent ref="ID00006"/>
    <parent ref="ID00004"/>
    <parent ref="ID00008"/>
    <parent ref="ID00043"/>
    <parent ref="ID00034"/>
    <parent ref="ID00045"/>
    <parent ref="ID00032"/>
    <parent ref="ID00021"/>
    <parent ref="ID00030"/>
    <parent ref="ID00013"/>
    <parent ref="ID00041"/>
    <parent ref="ID00010"/>
    <parent ref="ID00024"/>
    <parent ref="ID00017"/>
    <parent ref="ID00026"/>
    <parent ref="ID00015"/>
    <parent ref="ID00028"/>
    <parent ref="ID00047"/>
    <parent ref="ID00039"/>
    <parent ref="ID00049"/>
    <parent ref="ID00037"/>
    <parent ref="ID00019"/>
  </child>
  <child ref="ID00001">
    <parent ref="ID00005"/>
    <parent ref="ID00003"/>
    <parent ref="ID00009"/>
    <parent ref="ID00007"/>
    <parent ref="ID00044"/>
    <parent ref="ID00046"/>
    <parent ref="ID00033"/>
    <parent ref="ID00020"/>
    <parent ref="ID00012"/>
    <parent ref="ID00040"/>
    <parent ref="ID00031"/>
    <parent ref="ID00023"/>
    <parent ref="ID00042"/>
    <parent ref="ID00016"/>
    <parent ref="ID00025"/>
    <parent ref="ID00014"/>
    <parent ref="ID00027"/>
    <parent ref="ID00038"/>
    <parent ref="ID00029"/>
    <parent ref="ID00048"/>
    <parent ref="ID00036"/>
    <parent ref="ID00018"/>
  </child>
  <child ref="ID00003">
    <parent ref="ID00002"/>
  </child>
  <child ref="ID00004">
    <parent ref="ID00003"/>
  </child>
  <child ref="ID00005">
    <parent ref="ID00002"/>
  </child>
  <child ref="ID00006">
    <parent ref="ID00005"/>
  </child>
  <child ref="ID00007">
    <parent ref="ID00002"/>
  </child>
  <child ref="ID00008">
    <parent ref="ID00007"/>
  </child>
  <child ref="ID00009">
    <parent ref="ID00002"/>
  </child>
  <child ref="ID00010">
    <parent ref="ID00009"/>
  </child>
  <child ref="ID00012">
    <parent ref="ID00011"/>
  </child>
  <child ref="ID00013">
    <parent ref="ID00012"/>
  </child>
  <child ref="ID00014">
    <parent ref="ID00011"/>
  </child>
  <child ref="ID00015">
    <parent ref="ID00014"/>
  </child>
  <child ref="ID00016">
    <parent ref="ID00011"/>
  </child>
  <child ref="ID00017">
    <parent ref="ID00016"/>
  </child>
  <child ref="ID00018">
    <parent ref="ID00011"/>
  </child>
  <child ref="ID00019">
    <parent ref="ID00018"/>
  </child>
  <child ref="ID00020">
    <parent ref="ID00011"/>
  </child>
  <child ref="ID00021">
    <parent ref="ID00020"/>
  </child>
  <child ref="ID00023">
    <parent ref="ID00022"/>
  </child>
  <child ref="ID00024">
    <parent ref="ID00023"/>
  </child>
  <child ref="ID00025">
    <parent ref="ID00022"/>
  </child>
  <child ref="ID00026">
    <parent ref="ID00025"/>
  </child>
  <child ref="ID00027">
    <parent ref="ID00022"/>
  </child>
  <child ref="ID00028">
    <parent ref="ID00027"/>
  </child>
  <child ref="ID00029">
    <parent ref="ID00022"/>
  </child>
  <child ref="ID00030">
    <parent ref="ID00029"/>
  </child>
  <child ref="ID00031">
    <parent ref="ID00022"/>
  </child>
  <child ref="ID00032">
    <parent ref="ID00031"/>
  </child>
  <child ref="ID00033">
    <parent ref="ID00022"/>
  </child>
  <child ref="ID00034">
    <parent ref="ID00033"/>
  </child>
  <child ref="ID00036">
    <parent ref="ID00035"/>
  </child>
  <child ref="ID00037">
    <parent ref="ID00036"/>
  </child>
  <child ref="ID00038">
    <parent ref="ID00035"/>
  </child>
  <child ref="ID00039">
    <parent ref="ID00038"/>
  </child>
  <child ref="ID00040">
    <parent ref="ID00035"/>
  </child>
  <child ref="ID00041">
    <parent ref="ID00040"/>
  </child>
  <child ref="ID00042">
    <parent ref="ID00035"/>
  </child>
  <child ref="ID00043">
    <parent ref="ID00042"/>
  </child>
  <child ref="ID00044">
    <parent ref="ID00035"/>
  </child>
  <child ref="ID00045">
    <parent ref="ID00044"/>
  </child>
  <child ref="ID00046">
    <parent ref="ID00035"/>
  </child>
  <child ref="ID00047">
    <parent ref="ID00046"/>
  </child>
  <child ref="ID00048">
    <parent ref="ID00035"/>
  </child>
  <child ref="ID00049">
    <parent ref="ID00048"/>
  </child>
</adag>
